Metadata-Version: 2.1
Name: odoo12-addon-partner-contact-in-several-companies
Version: 12.0.2.0.0
Summary: Allow to have one contact in several partners
Home-page: https://github.com/OCA/partner-contact
Author: Nicolas JEUDY, Odoo Community Association (OCA),Odoo SA
Author-email: support@odoo-community.org
License: AGPL-3
Platform: UNKNOWN
Classifier: Programming Language :: Python
Classifier: Framework :: Odoo
Classifier: License :: OSI Approved :: GNU Affero General Public License v3
Requires-Python: >=3.5
Requires-Dist: odoo12-addon-partner-contact-personal-information-page
Requires-Dist: odoo (<12.1dev,>=12.0a)
